{
  "keyword": "wireless earbuds",
  "seo_metrics": {
    "search_volume": 165000,
    "keyword_difficulty": 72,
    "avg_cpc": 1.45
  },
  "content": "# Wireless Earbuds: The Ultimate Guide to Freedom from Cords\n=================================================================\n\nAre you tired of being tangled up in cords and earbuds that just can't seem to stay put? Look no further! Wireless earbuds have taken the world by storm, offering a sleek, convenient, and high-quality listening experience that's hard to beat. With so many options on the market, it can be overwhelming to choose the best pair for your needs. In this comprehensive guide, we'll dive into the world of wireless earbuds, exploring the best options, reviews, and comparisons to help you make an informed decision.\n\n## What to Look for in Wireless Earbuds\n------------------------------------\n\nWhen shopping for wireless earbuds, there are several key factors to consider. Sound quality, battery life, and price are just a few things to keep in mind. Here are some of the top features to look for:\n\n* **Sound Quality**: Look for earbuds with clear, crisp sound and good bass response. Some earbuds, like the [Sony WF-1000XM4]({AFF_LINK_1}), offer industry-leading sound quality with advanced noise-cancellation technology.\n* **Battery Life**: Consider earbuds with long battery life, such as the [Apple AirPods Pro]({AFF_LINK_2}), which offer up to 5 hours of listening time on a single charge.\n* **Price**: Wireless earbuds can range from under $50 to over $200, so set a budget and look for options that fit within it. For an affordable option, check out the [Anker Soundcore Liberty 2 Pro]({AFF_LINK_3}), which offers great sound quality at a fraction of the cost.\n\n## Top Wireless Earbuds Reviews\n-------------------------------\n\nWith so many great options on the market, it can be hard to choose the best wireless earbuds for your needs. Here are some of the top-rated earbuds in various categories:\n\n* **Best Overall**: [Sennheiser Momentum True Wireless 2]({AFF_LINK_1}) - These earbuds offer exceptional sound quality, long battery life, and a sleek design.\n* **Best Budget**: [Anker Soundcore Liberty 2 Pro]({AFF_LINK_3}) - These affordable earbuds offer great sound quality and long battery life at a fraction of the cost of some other options.\n* **Best for Fitness**: [Jabra Elite 75t]({AFF_LINK_2}) - These earbuds are designed for fitness enthusiasts, with a secure fit and sweat-resistant design.\n\n## Wireless Earbuds Comparison\n-----------------------------\n\nWith so many great options on the market, it can be hard to choose the best wireless earbuds for your needs. Here's a comparison of some of the top-rated earbuds:\n\n| Earbuds | Sound Quality | Battery Life | Price |\n| --- | --- | --- | --- |\n| Sony WF-1000XM4 | 5/5 | 6 hours | $229 |\n| Apple AirPods Pro | 4.5/5 | 5 hours | $249 |\n| Sennheiser Momentum True Wireless 2 | 5/5 | 7.5 hours | $299 |\n| Anker Soundcore Liberty 2 Pro | 4/5 | 8 hours | $69 |\n\n## Affordable Wireless Earbuds Options\n--------------------------------------\n\nNot everyone wants to break the bank on wireless earbuds. Here are some affordable options that still offer great sound quality and features:\n\n* **Anker Soundcore Liberty 2 Pro**: These earbuds offer great sound quality and long battery life at a fraction of the cost of some other options.\n* **Edifier TWS50**: These earbuds offer good sound quality and a sleek design at an affordable price point.\n\n## Conclusion and Call to Action\n--------------------------------\n\nWireless earbuds have come a long way in recent years, offering a convenient, high-quality listening experience that's hard to beat. Whether you're looking for the best sound quality, long battery life, or an affordable option, there's a pair of wireless earbuds out there for you. We hope this guide has helped you make an informed decision about which earbuds are right for you. Ready to take the plunge and experience the freedom of wireless earbuds? [Check out our top picks]({AFF_LINK_1}) and start shopping today!",
  "generated_at": "2025-06-04T01:39:11.660196",
  "affiliate_links": [
    "https://amazon.com/products/wireless-earbuds-1",
    "https://bestbuy.com/products/wireless-earbuds-2",
    "https://walmart.com/products/wireless-earbuds-3"
  ]
}